README.md
setup.py
gestor/__init__.py
gestor/getUSB.py
getUSB.egg-info/PKG-INFO
getUSB.egg-info/SOURCES.txt
getUSB.egg-info/dependency_links.txt
getUSB.egg-info/top_level.txt