Metadata-Version: 2.1
Name: getUSB
Version: 0.1
Summary: A package to get USB devices
Author: Pere Garau
